{
  "SPDXID": "SPDXRef-DOCUMENT",
  "name": "kuadrant/gateway-api-state-metrics 0.3.0",
  "spdxVersion": "SPDX-2.3",
  "creationInfo": {
    "created": "2026-03-06T19:51:59Z",
    "creators": [
      "Tool: bom-v0.7.1",
      "Tool: cncf-automation-sbom-generator"
    ],
    "licenseListVersion": "3.27",
    "comment": "SBOM for CNCF project: kuadrant/gateway-api-state-metrics@0.3.0"
  },
  "dataLicense": "CC0-1.0",
  "documentNamespace": "https://github.com/kuadrant/gateway-api-state-metrics/releases/tag/0.3.0",
  "documentDescribes": [
    "SPDXRef-Package-tmp.PYkjneyP8Y"
  ],
  "files": [
    {
      "SPDXID": "SPDXRef-File-tmp.PYkjneyP8Y-.github-workflows-ci.yaml",
      "fileName": ".github/workflows/ci.yaml",
      "copyrightText": "NOASSERTION",
      "licenseConcluded": "Apache-2.0",
      "fileTypes": [
        "TEXT"
      ],
      "licenseInfoInFiles": [
        "NONE"
      ],
      "checksums": [
        {
          "algorithm": "SHA256",
          "checksumValue": "cd68599629a6c756519ed153d5281088092fe4c9b092a639c06715eacfdbd931"
        },
        {
          "algorithm": "SHA512",
          "checksumValue": "38ffab03d6ef04980081e0c19a69e49aa9f5993573397cbca9b37d595b0591b5451d8c4ec5af23622247228bb4a6b8e45735d1e1c2b5e35cd5d5282fdc532645"
        },
        {
          "algorithm": "SHA1",
          "checksumValue": "0ac4e3c4da85e8c3b0f51ece3416957f0ddb60e7"
        }
      ]
    },
    {
      "SPDXID": "SPDXRef-File-tmp.PYkjneyP8Y-config-default-kustomization.yaml",
      "fileName": "config/default/kustomization.yaml",
      "copyrightText": "NOASSERTION",
      "licenseConcluded": "Apache-2.0",
      "fileTypes": [
        "TEXT"
      ],
      "licenseInfoInFiles": [
        "NONE"
      ],
      "checksums": [
        {
          "algorithm": "SHA1",
          "checksumValue": "294599e00010e8da2ed8aa87c573ff0d3e996de2"
        },
        {
          "algorithm": "SHA256",
          "checksumValue": "461d66bdb0660b1db8d0ee916508fb1108d9fae5d8f56c733f21258afee1b3e0"
        },
        {
          "algorithm": "SHA512",
          "checksumValue": "089fe89abe57936c5fcaf62e6b4c3fad85ad250e7c4a310b5b8ca98ea8c9c9b28fc3cfbf87fffc0e8d5a18dc0ae7ebe74775f7a17854dbe7302da48f151dec1a"
        }
      ]
    },
    {
      "SPDXID": "SPDXRef-File-tmp.PYkjneyP8Y-config-examples-kube-prometheus-README.md",
      "fileName": "config/examples/kube-prometheus/README.md",
      "copyrightText": "NOASSERTION",
      "licenseConcluded": "Apache-2.0",
      "fileTypes": [
        "TEXT",
        "DOCUMENTATION"
      ],
      "licenseInfoInFiles": [
        "NONE"
      ],
      "checksums": [
        {
          "algorithm": "SHA256",
          "checksumValue": "c74bda6a78814328c3c085571e5083cf49c3aa444056b19e2a236b07cbf18e76"
        },
        {
          "algorithm": "SHA512",
          "checksumValue": "2074606d4c93ead5d2af145058f9c0302796b1714bcbd76fd25080bc28f62abd5fda2847fa336e7cadcea2155c54f2c55de91acc32876a52c3b002b33d58dac3"
        },
        {
          "algorithm": "SHA1",
          "checksumValue": "db3dc54a9ae0de553b5ff54d7d1411e5f405c150"
        }
      ]
    },
    {
      "SPDXID": "SPDXRef-File-tmp.PYkjneyP8Y-config-examples-kube-prometheus-kustomization.yaml",
      "fileName": "config/examples/kube-prometheus/kustomization.yaml",
      "copyrightText": "NOASSERTION",
      "licenseConcluded": "Apache-2.0",
      "fileTypes": [
        "TEXT"
      ],
      "licenseInfoInFiles": [
        "NONE"
      ],
      "checksums": [
        {
          "algorithm": "SHA1",
          "checksumValue": "8f7364de7f1568c440b8986dc312ade42ef202ba"
        },
        {
          "algorithm": "SHA256",
          "checksumValue": "f37a99fcdb7866fca0431f8e62e32adb0600bded187346c78e558eb5da0fa461"
        },
        {
          "algorithm": "SHA512",
          "checksumValue": "63919417ff5f426761b64b0273dcdfc94558cbbff73f601ab294c83989f248e8fe2c4934a6bfeb0b99b3250082db16775e805da4507115b710205657fced09ba"
        }
      ]
    },
    {
      "SPDXID": "SPDXRef-File-tmp.PYkjneyP8Y-httproutes.png",
      "fileName": "httproutes.png",
      "copyrightText": "NOASSERTION",
      "licenseConcluded": "Apache-2.0",
      "fileTypes": [
        "IMAGE"
      ],
      "licenseInfoInFiles": [
        "NONE"
      ],
      "checksums": [
        {
          "algorithm": "SHA1",
          "checksumValue": "67e13f8ce4e15f93276812ed6c168cc79105695f"
        },
        {
          "algorithm": "SHA256",
          "checksumValue": "bc94645d71b02b15fb43999b09036a713893693fc19dc3a42a55eaa086f4f390"
        },
        {
          "algorithm": "SHA512",
          "checksumValue": "277474100accafeb7d015bde221b3c81df2989b9d8f16d38bdb3ae15d32b54f7a8d6543dc26d95be602207c37039665fdc0f723849b17ee30dbe62fca640b86f"
        }
      ]
    },
    {
      "SPDXID": "SPDXRef-File-tmp.PYkjneyP8Y-tests-manifests-testtlsroute1.yaml",
      "fileName": "tests/manifests/testtlsroute1.yaml",
      "copyrightText": "NOASSERTION",
      "licenseConcluded": "Apache-2.0",
      "fileTypes": [
        "TEXT"
      ],
      "licenseInfoInFiles": [
        "NONE"
      ],
      "checksums": [
        {
          "algorithm": "SHA512",
          "checksumValue": "679e834833fc2eacac8d33a505a46b155b6daf96f920c99989f988dab1ca79f157286b21aa818ae11e1392399c8e00989320b4ffeda95b161e49bd630a9b1b41"
        },
        {
          "algorithm": "SHA1",
          "checksumValue": "115172c9f52b6c06545157563e2904cf7a28b363"
        },
        {
          "algorithm": "SHA256",
          "checksumValue": "5962eb42315031b56a7fa55981d0b3d9ecca33b1026b7ddc25337e80ea912b88"
        }
      ]
    },
    {
      "SPDXID": "SPDXRef-File-tmp.PYkjneyP8Y-udproutes.png",
      "fileName": "udproutes.png",
      "copyrightText": "NOASSERTION",
      "licenseConcluded": "Apache-2.0",
      "fileTypes": [
        "IMAGE"
      ],
      "licenseInfoInFiles": [
        "NONE"
      ],
      "checksums": [
        {
          "algorithm": "SHA512",
          "checksumValue": "8e0d8a379f8f6b7dc4046408caf7fdd8aafd2dd4413bb19bae2f91c1a4242f331136b1a7cced0307a6987dad88bb6933f7bf3e8a480fbcfcb97a7d80322c4dcf"
        },
        {
          "algorithm": "SHA1",
          "checksumValue": "bdedc22ae495f5285c6b4ab31a5acf7db6b26189"
        },
        {
          "algorithm": "SHA256",
          "checksumValue": "c7de15bb45b6efbf23fd9af65a02f52c4a99d6cbedfba4dbd93a320385741eee"
        }
      ]
    },
    {
      "SPDXID": "SPDXRef-File-tmp.PYkjneyP8Y-config-gateway-api-crd-standard-gateway.networking.k8s.ioC95grpcroutes.yaml",
      "fileName": "config/gateway-api/crd/standard/gateway.networking.k8s.io_grpcroutes.yaml",
      "copyrightText": "NOASSERTION",
      "licenseConcluded": "Apache-2.0",
      "fileTypes": [
        "TEXT"
      ],
      "licenseInfoInFiles": [
        "NONE"
      ],
      "checksums": [
        {
          "algorithm": "SHA1",
          "checksumValue": "098d7a239d7ed21c99b0477686176f2240443afc"
        },
        {
          "algorithm": "SHA256",
          "checksumValue": "a5e012a3d6e2d4f715e0027031f43d8d3ac23b5deac17b3c21e8f5305b838107"
        },
        {
          "algorithm": "SHA512",
          "checksumValue": "44b177eec845301725ed5cb5bbda75f071115427b2ed73b66c2ca8e08c0bfb33b50284d293073756707b3aa1d23bce6566ed2cc7d4413a038186328400a1d3ce"
        }
      ]
    },
    {
      "SPDXID": "SPDXRef-File-tmp.PYkjneyP8Y-config-examples-kube-prometheus-grafanaC95deploymentC95patch.yaml",
      "fileName": "config/examples/kube-prometheus/grafana_deployment_patch.yaml",
      "copyrightText": "NOASSERTION",
      "licenseConcluded": "Apache-2.0",
      "fileTypes": [
        "TEXT"
      ],
      "licenseInfoInFiles": [
        "NONE"
      ],
      "checksums": [
        {
          "algorithm": "SHA1",
          "checksumValue": "58d6d0c09ff6af7260f5bd9009dca587d8890b20"
        },
        {
          "algorithm": "SHA256",
          "checksumValue": "731e56b7a9dff33217386c79d0d7263e01e92daa08e6831025c91072e99fd50e"
        },
        {
          "algorithm": "SHA512",
          "checksumValue": "9d00ffaeb497a73df496786139b9df59808099bcedc70c05676fa6b215eef59d123c289f65f298ca5ac2ea6dd35300a6a0d801287bba005a4a02da5e7a7260e3"
        }
      ]
    },
    {
      "SPDXID": "SPDXRef-File-tmp.PYkjneyP8Y-config-gateway-api-crd-standard-gateway.networking.k8s.ioC95gatewayclasses.yaml",
      "fileName": "config/gateway-api/crd/standard/gateway.networking.k8s.io_gatewayclasses.yaml",
      "copyrightText": "NOASSERTION",
      "licenseConcluded": "Apache-2.0",
      "fileTypes": [
        "TEXT"
      ],
      "licenseInfoInFiles": [
        "NONE"
      ],
      "checksums": [
        {
          "algorithm": "SHA256",
          "checksumValue": "38aa141d1754910cbb9adc199e3de499eb8bccbfda565d5c01fe48a736fea472"
        },
        {
          "algorithm": "SHA512",
          "checksumValue": "bd06ca8fc87e012e1bf4a949732de44c08280c09950e11d8b18831fa7b84422d37b5124e34a5bacb4eefaae8fd132522a0e21efd4155c1357d09d3c4cc20f04a"
        },
        {
          "algorithm": "SHA1",
          "checksumValue": "553dac45ac8e58fb8076c9192fc4fe81aec17a98"
        }
      ]
    },
    {
      "SPDXID": "SPDXRef-File-tmp.PYkjneyP8Y-config-examples-dashboards-gatewayclasses.json",
      "fileName": "config/examples/dashboards/gatewayclasses.json",
      "copyrightText": "NOASSERTION",
      "licenseConcluded": "Apache-2.0",
      "fileTypes": [
        "TEXT"
      ],
      "licenseInfoInFiles": [
        "NONE"
      ],
      "checksums": [
        {
          "algorithm": "SHA1",
          "checksumValue": "43261436730ac769573b7247116d5642b1736683"
        },
        {
          "algorithm": "SHA256",
          "checksumValue": "0c12c2e5457893a29829f1265a26f991f3994cec9eaaec37076f47f17052f7c3"
        },
        {
          "algorithm": "SHA512",
          "checksumValue": "24c0c4a464cd3f24d73adf3dfe86e164296f9992e14d922ece6e961dc778cd6b7440f7d74432575eb9031374d02df2d20e54729e898423144d507c262df4ad05"
        }
      ]
    },
    {
      "SPDXID": "SPDXRef-File-tmp.PYkjneyP8Y-tests-manifests-testgrpcroute1.yaml",
      "fileName": "tests/manifests/testgrpcroute1.yaml",
      "copyrightText": "NOASSERTION",
      "licenseConcluded": "Apache-2.0",
      "fileTypes": [
        "TEXT"
      ],
      "licenseInfoInFiles": [
        "NONE"
      ],
      "checksums": [
        {
          "algorithm": "SHA1",
          "checksumValue": "0cbb58cc5bebfb237131d963f5a08a5e3ce9ffb5"
        },
        {
          "algorithm": "SHA256",
          "checksumValue": "92c0de4c355fb80501f1e7e339bd565baf59688871c407f12001fac0e45e1828"
        },
        {
          "algorithm": "SHA512",
          "checksumValue": "736f26474463864956344ca0ee8a319c9b671e806a01b5188d789b11b07927a0f90b81e4e8422db084ac3ed4836a4b75dc9e2edf77d07b2695a4bf7842dddbb5"
        }
      ]
    },
    {
      "SPDXID": "SPDXRef-File-tmp.PYkjneyP8Y-tcproutes.png",
      "fileName": "tcproutes.png",
      "copyrightText": "NOASSERTION",
      "licenseConcluded": "Apache-2.0",
      "fileTypes": [
        "IMAGE"
      ],
      "licenseInfoInFiles": [
        "NONE"
      ],
      "checksums": [
        {
          "algorithm": "SHA1",
          "checksumValue": "0fa229148211e3be96c7e77e1d4c17cf4ca7d774"
        },
        {
          "algorithm": "SHA256",
          "checksumValue": "e6d19036a8de39edf3ff471ccedca1e2e54aef8a336ca2fa2c088fc470360de2"
        },
        {
          "algorithm": "SHA512",
          "checksumValue": "d81a043144ba8aa6e34716b17a0af0354cd3fd15b1811895443957b1e6ab118c21183212fdd21a78bede879190f0b05c8ed3521bbbe9776ae5abcba58bcfc864"
        }
      ]
    },
    {
      "SPDXID": "SPDXRef-File-tmp.PYkjneyP8Y-tests-e2e-mainC95test.go",
      "fileName": "tests/e2e/main_test.go",
      "copyrightText": "NOASSERTION",
      "licenseConcluded": "Apache-2.0",
      "fileTypes": [
        "SOURCE"
      ],
      "licenseInfoInFiles": [
        "NONE"
      ],
      "checksums": [
        {
          "algorithm": "SHA1",
          "checksumValue": "3d1cf47f39a232e1a5530994c1a92f67f97c3443"
        },
        {
          "algorithm": "SHA256",
          "checksumValue": "8364ed2ee5ca37f7a13c0da5dbd826ce4735f27182fef4f1101f36fdeaff99fa"
        },
        {
          "algorithm": "SHA512",
          "checksumValue": "d80c856bb4c9039f59e1050f6c28c1217391fa5dd75f0615494c31113e1a306c182bde57d07c89dd925a737151c2526cc69ac6e20780770e4425a63734c94967"
        }
      ]
    },
    {
      "SPDXID": "SPDXRef-File-tmp.PYkjneyP8Y-config-examples-dashboards-grpcroutes.json",
      "fileName": "config/examples/dashboards/grpcroutes.json",
      "copyrightText": "NOASSERTION",
      "licenseConcluded": "Apache-2.0",
      "fileTypes": [
        "TEXT"
      ],
      "licenseInfoInFiles": [
        "NONE"
      ],
      "checksums": [
        {
          "algorithm": "SHA256",
          "checksumValue": "5ccf2ef66b37d7000d1d2f948e8120096f71baec477cba6aec96c7e0f76498dc"
        },
        {
          "algorithm": "SHA512",
          "checksumValue": "0872e31d0588fbca1145828ea5e1c173642483532a855b457bad7ca1b757bce05cea6b5501c37833ae32d3ef8497269b5b8b898977f49d250983c29a2ee65b32"
        },
        {
          "algorithm": "SHA1",
          "checksumValue": "0c12528a666c07ffd658f18f56078ca850eb23be"
        }
      ]
    },
    {
      "SPDXID": "SPDXRef-File-tmp.PYkjneyP8Y-config-gateway-api-kustomization.yaml",
      "fileName": "config/gateway-api/kustomization.yaml",
      "copyrightText": "NOASSERTION",
      "licenseConcluded": "Apache-2.0",
      "fileTypes": [
        "TEXT"
      ],
      "licenseInfoInFiles": [
        "NONE"
      ],
      "checksums": [
        {
          "algorithm": "SHA1",
          "checksumValue": "fee9fce0d3e23d77f4309d7e1b132dedb7b99b20"
        },
        {
          "algorithm": "SHA256",
          "checksumValue": "78971e5180fce580062b1b8fe58bd48c33a27c279962822ae82d2d0e8e25cbb4"
        },
        {
          "algorithm": "SHA512",
          "checksumValue": "c21926a54cd14cb3c2e4b10a3f84573aa137225eb3d533a3db17c9fe8bcfb272c09dd81af1b168fe0e79cf3b4c67bc468d2d76c25523bc11155366a54bfe8dd8"
        }
      ]
    },
    {
      "SPDXID": "SPDXRef-File-tmp.PYkjneyP8Y-tests-manifests-testgatewayclass1.yaml",
      "fileName": "tests/manifests/testgatewayclass1.yaml",
      "copyrightText": "NOASSERTION",
      "licenseConcluded": "Apache-2.0",
      "fileTypes": [
        "TEXT"
      ],
      "licenseInfoInFiles": [
        "NONE"
      ],
      "checksums": [
        {
          "algorithm": "SHA1",
          "checksumValue": "f65107357a75f09c789099cb26c5c55b03300130"
        },
        {
          "algorithm": "SHA256",
          "checksumValue": "3792b9c02b40101e6d0828e48cf0fcdabf4ddfe72792c56a0e28bc80bf2aa290"
        },
        {
          "algorithm": "SHA512",
          "checksumValue": "fa50b10d4dfcb9bc1e14bf397a64ba83fec796b8e1ddc2012401d3d656dbd036fe843b121ab16a5a39885a9803515e5be00d64e7c19b10f97f3ad17402b368fa"
        }
      ]
    },
    {
      "SPDXID": "SPDXRef-File-tmp.PYkjneyP8Y-config-examples-dashboards-gateways.json",
      "fileName": "config/examples/dashboards/gateways.json",
      "copyrightText": "NOASSERTION",
      "licenseConcluded": "Apache-2.0",
      "fileTypes": [
        "TEXT"
      ],
      "licenseInfoInFiles": [
        "NONE"
      ],
      "checksums": [
        {
          "algorithm": "SHA256",
          "checksumValue": "835465fa5840250e99564baad499f814da41d220c09d0a718218f8d44c879257"
        },
        {
          "algorithm": "SHA512",
          "checksumValue": "af9c751e023bcd8e3f8581a8c3a8152fed473ca9235015edbe7c95b248ae233636dca51f8c07d8e502c2d9bd5249d5374d6e72ac3fd693d15eba14dc7e8c1fdf"
        },
        {
          "algorithm": "SHA1",
          "checksumValue": "526d3db142b87eee463e81d5a15e022758715e77"
        }
      ]
    },
    {
      "SPDXID": "SPDXRef-File-tmp.PYkjneyP8Y-.gitignore",
      "fileName": ".gitignore",
      "copyrightText": "NOASSERTION",
      "licenseConcluded": "Apache-2.0",
      "fileTypes": [
        "OTHER"
      ],
      "licenseInfoInFiles": [
        "NONE"
      ],
      "checksums": [
        {
          "algorithm": "SHA1",
          "checksumValue": "247199cd22ddb5512f928232846194127a19cec3"
        },
        {
          "algorithm": "SHA256",
          "checksumValue": "626a3de8411efd0c5401bcaf407cea781d4b5ba7f47f29a554d00bbd457e74ae"
        },
        {
          "algorithm": "SHA512",
          "checksumValue": "c9777ddc8cb4ae01bacee94179789abcb0c2078d63f80be29629c33d2099c6e6c86ed26fb84d931f306f17959f366fce8613a72c1688e9194228501f01dd0b1c"
        }
      ]
    },
    {
      "SPDXID": "SPDXRef-File-tmp.PYkjneyP8Y-config-examples-kube-state-metrics-deployment.yaml",
      "fileName": "config/examples/kube-state-metrics/deployment.yaml",
      "copyrightText": "NOASSERTION",
      "licenseConcluded": "Apache-2.0",
      "fileTypes": [
        "TEXT"
      ],
      "licenseInfoInFiles": [
        "NONE"
      ],
      "checksums": [
        {
          "algorithm": "SHA1",
          "checksumValue": "27d0d3c412ee6f59552e86612e8ff36bb7604cf6"
        },
        {
          "algorithm": "SHA256",
          "checksumValue": "42df0d136cfac95049c25e16c6e8228e1362db24b45beccfc8612f0cbfe17300"
        },
        {
          "algorithm": "SHA512",
          "checksumValue": "1c9e785aa67db031e894bf8bf8a0b514347018d2ef7908754dc1b38caf84ef4c7b979b570d3a7b0de9929a8be2f5106311c89ec3aaaf12ab5176ec804d8ce86a"
        }
      ]
    },
    {
      "SPDXID": "SPDXRef-File-tmp.PYkjneyP8Y-config-examples-dashboards-kustomization.yaml",
      "fileName": "config/examples/dashboards/kustomization.yaml",
      "copyrightText": "NOASSERTION",
      "licenseConcluded": "Apache-2.0",
      "fileTypes": [
        "TEXT"
      ],
      "licenseInfoInFiles": [
        "NONE"
      ],
      "checksums": [
        {
          "algorithm": "SHA1",
          "checksumValue": "0f7e7919d866b6364411d64678c0aca36b99deeb"
        },
        {
          "algorithm": "SHA256",
          "checksumValue": "e7e0434e8c323dfa88bda41e81b68c958ac43939252223ca39736b264bc0acd7"
        },
        {
          "algorithm": "SHA512",
          "checksumValue": "0415dd1a57c36ce3b64bb4c59332edbf724a8531de5bfed60a38b95d64692c471e627078a4e983006fe16cf32f06cb24e20993db991aaa9f8a2733c5a5428502"
        }
      ]
    },
    {
      "SPDXID": "SPDXRef-File-tmp.PYkjneyP8Y-Makefile",
      "fileName": "Makefile",
      "copyrightText": "NOASSERTION",
      "licenseConcluded": "Apache-2.0",
      "fileTypes": [
        "TEXT",
        "DOCUMENTATION"
      ],
      "licenseInfoInFiles": [
        "NONE"
      ],
      "checksums": [
        {
          "algorithm": "SHA1",
          "checksumValue": "b370e45e2b5f3f861dd35f7dc7d226a3641f4530"
        },
        {
          "algorithm": "SHA256",
          "checksumValue": "8bdbd026de3868b2ef1957eef116004022b40458ef411b26a0a079b519bd8b2b"
        },
        {
          "algorithm": "SHA512",
          "checksumValue": "4037e6b53ae7f2c4aea5480d091e06dca48e6d9b93660f927c9761f3b296c424489552b3eb5f82d0823a414708cd347df52a6483941452f3fe621d88d04fed85"
        }
      ]
    },
    {
      "SPDXID": "SPDXRef-File-tmp.PYkjneyP8Y-gatewayclasses.png",
      "fileName": "gatewayclasses.png",
      "copyrightText": "NOASSERTION",
      "licenseConcluded": "Apache-2.0",
      "fileTypes": [
        "IMAGE"
      ],
      "licenseInfoInFiles": [
        "NONE"
      ],
      "checksums": [
        {
          "algorithm": "SHA1",
          "checksumValue": "4196d1bf450b4210d3487c336e4e446dda491c37"
        },
        {
          "algorithm": "SHA256",
          "checksumValue": "62dff8c9ee1fcbe2d8b6b38a640cb58532870b5f9b68de465281522645fe292d"
        },
        {
          "algorithm": "SHA512",
          "checksumValue": "d017aeab729fa8073fd239d03d9c38abd5eff093db1a6d0639af0ddee2edf1356ca8c3d571cd2db07bd8b8aa3ebe1664b27c041054920f4fbcd31e7dc5d7a05a"
        }
      ]
    },
    {
      "SPDXID": "SPDXRef-File-tmp.PYkjneyP8Y-config-gateway-api-crd-standard-gateway.networking.k8s.ioC95tlsroutes.yaml",
      "fileName": "config/gateway-api/crd/standard/gateway.networking.k8s.io_tlsroutes.yaml",
      "copyrightText": "NOASSERTION",
      "licenseConcluded": "Apache-2.0",
      "fileTypes": [
        "TEXT"
      ],
      "licenseInfoInFiles": [
        "NONE"
      ],
      "checksums": [
        {
          "algorithm": "SHA1",
          "checksumValue": "480798e07231f9124e07aae973cddbdf9714dc23"
        },
        {
          "algorithm": "SHA256",
          "checksumValue": "88c20d30f8f64dfecc077e292314d14f415ac88ca42ebe516cc44d08757626ce"
        },
        {
          "algorithm": "SHA512",
          "checksumValue": "3bfdd0f3614e26bbf91f185786362290135fa26d25001389d07d9c704a4a8638412332d2526fead214d158e6b457a2faa2c3b8c0104ab0a6d75a4c25858a62e3"
        }
      ]
    },
    {
      "SPDXID": "SPDXRef-File-tmp.PYkjneyP8Y-tlsroutes.png",
      "fileName": "tlsroutes.png",
      "copyrightText": "NOASSERTION",
      "licenseConcluded": "Apache-2.0",
      "fileTypes": [
        "IMAGE"
      ],
      "licenseInfoInFiles": [
        "NONE"
      ],
      "checksums": [
        {
          "algorithm": "SHA512",
          "checksumValue": "7f19ebba7c13e852d136c16aa704e22c1132ee2cef08df596590229da9fe650352407afac3bbebcae2571a4cf95cbe5a47a07ad3c8c2c5e146aefd74145d3ed4"
        },
        {
          "algorithm": "SHA1",
          "checksumValue": "0577f88b999dae3ba903f61f271917b527271b63"
        },
        {
          "algorithm": "SHA256",
          "checksumValue": "279aebb65d5350961454049a5793353084244b8083787d7277a3a8b688d74bfc"
        }
      ]
    },
    {
      "SPDXID": "SPDXRef-File-tmp.PYkjneyP8Y-LICENSE",
      "fileName": "LICENSE",
      "copyrightText": "NOASSERTION",
      "licenseConcluded": "Apache-2.0",
      "fileTypes": [
        "TEXT",
        "DOCUMENTATION"
      ],
      "licenseInfoInFiles": [
        "Apache-2.0"
      ],
      "checksums": [
        {
          "algorithm": "SHA256",
          "checksumValue": "c71d239df91726fc519c6eb72d318ec65820627232b2f796219e87dcf35d0ab4"
        },
        {
          "algorithm": "SHA512",
          "checksumValue": "dc6b68d13b8cf959644b935f1192b02c71aa7a5cf653bd43b4480fa89eec8d4d3f16a2278ec8c3b40ab1fdb233b3173a78fd83590d6f739e0c9e8ff56c282557"
        },
        {
          "algorithm": "SHA1",
          "checksumValue": "7df059597099bb7dcf25d2a9aedfaf4465f72d8d"
        }
      ]
    },
    {
      "SPDXID": "SPDXRef-File-tmp.PYkjneyP8Y-config-examples-kube-state-metrics-cluster-role-binding.yaml",
      "fileName": "config/examples/kube-state-metrics/cluster-role-binding.yaml",
      "copyrightText": "NOASSERTION",
      "licenseConcluded": "Apache-2.0",
      "fileTypes": [
        "TEXT"
      ],
      "licenseInfoInFiles": [
        "NONE"
      ],
      "checksums": [
        {
          "algorithm": "SHA256",
          "checksumValue": "3e48e681b59f5c017f22ea98f43c056bd87462dfbae89142bcd038ddce4cd83a"
        },
        {
          "algorithm": "SHA512",
          "checksumValue": "aed0426f158b02300eb9540f1c34345a58751954312a34ddd20fa9334c459c404fc3d0ecd530cbd2a8e1a62597a62ca9b765693ec890500f373c7ad531f9697e"
        },
        {
          "algorithm": "SHA1",
          "checksumValue": "32f096bb73b239fc38013f6c3934ea0dc05f5630"
        }
      ]
    },
    {
      "SPDXID": "SPDXRef-File-tmp.PYkjneyP8Y-config-examples-kube-prometheus-bundle-README.md",
      "fileName": "config/examples/kube-prometheus/bundle-README.md",
      "copyrightText": "NOASSERTION",
      "licenseConcluded": "Apache-2.0",
      "fileTypes": [
        "TEXT",
        "DOCUMENTATION"
      ],
      "licenseInfoInFiles": [
        "NONE"
      ],
      "checksums": [
        {
          "algorithm": "SHA256",
          "checksumValue": "567f58ebacf350be8c727c75255d2202428ded8007b97b271c44fee0dbf02df6"
        },
        {
          "algorithm": "SHA512",
          "checksumValue": "ce4542ae7e26edb1ecaf937d0e404563dbc37f2c1912ddf409f54097063288a0fe5eb1c2ae21e30d99d11aa4aaa2b6dd30d3ab0ac0efbcc202a92369da2ebf6a"
        },
        {
          "algorithm": "SHA1",
          "checksumValue": "7afbd3200d6d492aa70d45cacb07a9bc3f1029e8"
        }
      ]
    },
    {
      "SPDXID": "SPDXRef-File-tmp.PYkjneyP8Y-README.md",
      "fileName": "README.md",
      "copyrightText": "NOASSERTION",
      "licenseConcluded": "Apache-2.0",
      "fileTypes": [
        "TEXT",
        "DOCUMENTATION"
      ],
      "licenseInfoInFiles": [
        "NONE"
      ],
      "checksums": [
        {
          "algorithm": "SHA512",
          "checksumValue": "712fca907bf3cdbca1449c13a91bf902f0d104c2b9a65d9ee128279ba73876b139bb113efbe859b4517afae8fd09dd9d683e850052d8795c4673d2e3aab04c03"
        },
        {
          "algorithm": "SHA1",
          "checksumValue": "95a96a30d4a52341b9e01410ac7b83165b7a42c4"
        },
        {
          "algorithm": "SHA256",
          "checksumValue": "7d2947bca20be12a0250988fb0618a55229607d41abb5011261c2cb8c169beed"
        }
      ]
    },
    {
      "SPDXID": "SPDXRef-File-tmp.PYkjneyP8Y-tests-manifests-testtcproute1.yaml",
      "fileName": "tests/manifests/testtcproute1.yaml",
      "copyrightText": "NOASSERTION",
      "licenseConcluded": "Apache-2.0",
      "fileTypes": [
        "TEXT"
      ],
      "licenseInfoInFiles": [
        "NONE"
      ],
      "checksums": [
        {
          "algorithm": "SHA1",
          "checksumValue": "b8b7a750e443852fecca0e921cc316bc7108c9b4"
        },
        {
          "algorithm": "SHA256",
          "checksumValue": "c373560932e80337be256b8b9684b7effd9867e37d4779a14be209249c4ab41e"
        },
        {
          "algorithm": "SHA512",
          "checksumValue": "11ef3ecc72f821cb48037ae1432cf4247f0387d2a3755ff8b4a28748296dbc373fc7cc24e6f192fb1dadc3a7b029f2ff3ece7bab352e227e30bd529639cb5fbc"
        }
      ]
    },
    {
      "SPDXID": "SPDXRef-File-tmp.PYkjneyP8Y-config-examples-rules-kustomization.yaml",
      "fileName": "config/examples/rules/kustomization.yaml",
      "copyrightText": "NOASSERTION",
      "licenseConcluded": "Apache-2.0",
      "fileTypes": [
        "TEXT"
      ],
      "licenseInfoInFiles": [
        "NONE"
      ],
      "checksums": [
        {
          "algorithm": "SHA1",
          "checksumValue": "d08424dfaf7d11c4ccde1251f3a0f21e82a53a93"
        },
        {
          "algorithm": "SHA256",
          "checksumValue": "4477c1df17dab50b46551a5d355aabacbd09d7a14625926154924c896ee2855a"
        },
        {
          "algorithm": "SHA512",
          "checksumValue": "a94ea011ad81a9ae3825f8331e74f625b56cd38bc0c2aac34c9f3b8a0f713cc7e8b787629be8b059916d01269dfbe1f37c9475bf651cc43d8d5462c808590231"
        }
      ]
    },
    {
      "SPDXID": "SPDXRef-File-tmp.PYkjneyP8Y-config-gateway-api-crd-standard-gateway.networking.k8s.ioC95gateways.yaml",
      "fileName": "config/gateway-api/crd/standard/gateway.networking.k8s.io_gateways.yaml",
      "copyrightText": "NOASSERTION",
      "licenseConcluded": "Apache-2.0",
      "fileTypes": [
        "TEXT"
      ],
      "licenseInfoInFiles": [
        "NONE"
      ],
      "checksums": [
        {
          "algorithm": "SHA512",
          "checksumValue": "4d97d5403615c7af1757411009f24fa015656748797f427ce59aa75c4d663a8ec5bdaa21ccc08725c34206ecafc732392294c484f1438f8fdf9806bed16c24f8"
        },
        {
          "algorithm": "SHA1",
          "checksumValue": "2e2dcc49b787df86fa5e8c76bffa8ead049eb36d"
        },
        {
          "algorithm": "SHA256",
          "checksumValue": "6491600e5ad1c3b144d72a187ece69aaa84983f584b8aee8d159034b6ce0f27a"
        }
      ]
    },
    {
      "SPDXID": "SPDXRef-File-tmp.PYkjneyP8Y-config-examples-kube-prometheus-bundleC95crd.yaml",
      "fileName": "config/examples/kube-prometheus/bundle_crd.yaml",
      "copyrightText": "NOASSERTION",
      "licenseConcluded": "Apache-2.0",
      "fileTypes": [
        "TEXT"
      ],
      "licenseInfoInFiles": [
        "NONE"
      ],
      "checksums": [
        {
          "algorithm": "SHA512",
          "checksumValue": "9f0f29bc84b5c3cfd51b6064ddc84ec08acbf25ca03def407b96779ddfb4d112b5e3a328c617d1b90bfb3de5c5cf56a032ea87b8dbd791fc085fdf21e833b74d"
        },
        {
          "algorithm": "SHA1",
          "checksumValue": "321313fff4ccd4a632e44438716884539fcd5ee9"
        },
        {
          "algorithm": "SHA256",
          "checksumValue": "3127435f678222fa01963f103d43312eadb3b616fb41d146da309367616fea12"
        }
      ]
    },
    {
      "SPDXID": "SPDXRef-File-tmp.PYkjneyP8Y-config-examples-rules-alert-rules.yaml",
      "fileName": "config/examples/rules/alert-rules.yaml",
      "copyrightText": "NOASSERTION",
      "licenseConcluded": "Apache-2.0",
      "fileTypes": [
        "TEXT"
      ],
      "licenseInfoInFiles": [
        "NONE"
      ],
      "checksums": [
        {
          "algorithm": "SHA1",
          "checksumValue": "515a6c4d672b9a8f4299dc91e2dafafcab150f0e"
        },
        {
          "algorithm": "SHA256",
          "checksumValue": "f6555126dd689a61efe39fc40a9662954aad97ca43de302238387182040538fe"
        },
        {
          "algorithm": "SHA512",
          "checksumValue": "40a46515ccaa98952e80efbf0b3a37847acf7d3405cbd883dda8cbd26f535f892b132513d94bd858fb2d6d69c7eea7a65031d6cef15edc5280f8065116f34403"
        }
      ]
    },
    {
      "SPDXID": "SPDXRef-File-tmp.PYkjneyP8Y-config-default-custom-resource-state.yaml",
      "fileName": "config/default/custom-resource-state.yaml",
      "copyrightText": "NOASSERTION",
      "licenseConcluded": "Apache-2.0",
      "fileTypes": [
        "TEXT"
      ],
      "licenseInfoInFiles": [
        "NONE"
      ],
      "checksums": [
        {
          "algorithm": "SHA1",
          "checksumValue": "39f3d09b8cc6c05619f0d8493010c1f7160cc4e7"
        },
        {
          "algorithm": "SHA256",
          "checksumValue": "b7a57b7da8d35d59c01ea266a15a305e5b05e76272409eefc9093380268a4317"
        },
        {
          "algorithm": "SHA512",
          "checksumValue": "e8b876ff54fcce0cc1ea0bff179a571f68613c4648ea43951bc9863e7d9eabf3a3dc053f8d2fd7f5e1e3f2a8ffb8bfcaefb78abb712d063590bb919c27746fda"
        }
      ]
    },
    {
      "SPDXID": "SPDXRef-File-tmp.PYkjneyP8Y-gateways.png",
      "fileName": "gateways.png",
      "copyrightText": "NOASSERTION",
      "licenseConcluded": "Apache-2.0",
      "fileTypes": [
        "IMAGE"
      ],
      "licenseInfoInFiles": [
        "NONE"
      ],
      "checksums": [
        {
          "algorithm": "SHA1",
          "checksumValue": "5f45db32bc597ac0043ff650520c548df9c8e339"
        },
        {
          "algorithm": "SHA256",
          "checksumValue": "44bc87798d5e31ec080d7f7299181995d5769b53e2d7a1ac3b396597215c2f38"
        },
        {
          "algorithm": "SHA512",
          "checksumValue": "3e8a870130245305b89ecb54461fe9588686fc2a8f0ab146496026ea9a78b9f4c007ace594ac9f4f789c9d8bd4dd70e4172017997ef971ff20fee014bf34252d"
        }
      ]
    },
    {
      "SPDXID": "SPDXRef-File-tmp.PYkjneyP8Y-go.sum",
      "fileName": "go.sum",
      "copyrightText": "NOASSERTION",
      "licenseConcluded": "Apache-2.0",
      "fileTypes": [
        "OTHER"
      ],
      "licenseInfoInFiles": [
        "NONE"
      ],
      "checksums": [
        {
          "algorithm": "SHA1",
          "checksumValue": "53fe2c352541998eb36019eeb5bfa85b30edceaa"
        },
        {
          "algorithm": "SHA256",
          "checksumValue": "782cd44432b5232e75b5bb3e4e3cb97742fa168617ba6a341b5312728a89618e"
        },
        {
          "algorithm": "SHA512",
          "checksumValue": "a2f2acd4cc9f2a01920c53724a4af32cc69924de7204003dac00d9a10dbcfd84ac68e89045602d634d2f18a1798a64529bc757a1aa15aa8159e5c59b3e9419b5"
        }
      ]
    },
    {
      "SPDXID": "SPDXRef-File-tmp.PYkjneyP8Y-go.mod",
      "fileName": "go.mod",
      "copyrightText": "NOASSERTION",
      "licenseConcluded": "Apache-2.0",
      "fileTypes": [
        "OTHER"
      ],
      "licenseInfoInFiles": [
        "NONE"
      ],
      "checksums": [
        {
          "algorithm": "SHA1",
          "checksumValue": "dc77d1294a2181224cab68451060c32d4416f905"
        },
        {
          "algorithm": "SHA256",
          "checksumValue": "ad3c037bcd8f4b5cfb5266dbb5b135219be5caba06806987e961ded88a3cd403"
        },
        {
          "algorithm": "SHA512",
          "checksumValue": "95043f69576c8b6d7a1eff4b3339bf0a85b4a37bc6a8c2fddc974e41de6794c1e75deee1a34ea240a0acaea3529c0b6ec3923cb0e80ebdcb73370d468530d6f4"
        }
      ]
    },
    {
      "SPDXID": "SPDXRef-File-tmp.PYkjneyP8Y-config-examples-dashboards-udproutes.json",
      "fileName": "config/examples/dashboards/udproutes.json",
      "copyrightText": "NOASSERTION",
      "licenseConcluded": "Apache-2.0",
      "fileTypes": [
        "TEXT"
      ],
      "licenseInfoInFiles": [
        "NONE"
      ],
      "checksums": [
        {
          "algorithm": "SHA1",
          "checksumValue": "793ebf072c2d7cc3f52465060d780c65bd94228f"
        },
        {
          "algorithm": "SHA256",
          "checksumValue": "b894b11f97462ac1cc3ebd317bbd10ea95edaaee23eaa91aa99194a4fb5a340f"
        },
        {
          "algorithm": "SHA512",
          "checksumValue": "54cdf0a618a42142ad5b082dbb6fc4ca3abfddbee077eff60c66c098074e5f7e395864b685efb23069c0370d382e36e759a7f0347c1ea83b7c3b2fd5c12c5a06"
        }
      ]
    },
    {
      "SPDXID": "SPDXRef-File-tmp.PYkjneyP8Y-grpcroutes.png",
      "fileName": "grpcroutes.png",
      "copyrightText": "NOASSERTION",
      "licenseConcluded": "Apache-2.0",
      "fileTypes": [
        "IMAGE"
      ],
      "licenseInfoInFiles": [
        "NONE"
      ],
      "checksums": [
        {
          "algorithm": "SHA1",
          "checksumValue": "d44e8cca663855d592e1f4fb535e39befe8035fd"
        },
        {
          "algorithm": "SHA256",
          "checksumValue": "87de5c17cb730bf47acde3fbcd5e76823655849dd6d2247c11e65e33e95926de"
        },
        {
          "algorithm": "SHA512",
          "checksumValue": "dfe394bba76ac70571ad5ec9ec87426e327dcbb234d66cb6002fb68d6724f3594296fca2788bc4b4d4c573ce5a30d9fdb40069ecead2b92a77ec29ff4c5d38df"
        }
      ]
    },
    {
      "SPDXID": "SPDXRef-File-tmp.PYkjneyP8Y-config-examples-dashboards-tcproutes.json",
      "fileName": "config/examples/dashboards/tcproutes.json",
      "copyrightText": "NOASSERTION",
      "licenseConcluded": "Apache-2.0",
      "fileTypes": [
        "TEXT"
      ],
      "licenseInfoInFiles": [
        "NONE"
      ],
      "checksums": [
        {
          "algorithm": "SHA1",
          "checksumValue": "8e9cc661bc59255e491e60ae111eb3542acfea0b"
        },
        {
          "algorithm": "SHA256",
          "checksumValue": "4e92823711e9ebe46309e82016e8d2cf046250582af6079c41e1acea38eab5a9"
        },
        {
          "algorithm": "SHA512",
          "checksumValue": "f66c4920c9f2c248250c57e2a0210819c16ac91598f12be4d8451b4e986294aaf615b944e0577d75e69a0e70cb8dca259bd1ea5ec2cccf5907eec04a42b810bb"
        }
      ]
    },
    {
      "SPDXID": "SPDXRef-File-tmp.PYkjneyP8Y-config-examples-kube-state-metrics-cluster-role.yaml",
      "fileName": "config/examples/kube-state-metrics/cluster-role.yaml",
      "copyrightText": "NOASSERTION",
      "licenseConcluded": "Apache-2.0",
      "fileTypes": [
        "TEXT"
      ],
      "licenseInfoInFiles": [
        "NONE"
      ],
      "checksums": [
        {
          "algorithm": "SHA512",
          "checksumValue": "e6e07d58bec9e4e132b2a04e0c1c7f84bcf5d86a061c1739f2c262fe2597dc2d4d520844d290a82bdd3ea3eb106c112dd2c9a1d9a02887042edaf2a57db0fc62"
        },
        {
          "algorithm": "SHA1",
          "checksumValue": "837d84fcdef540cf09872879300092e05fc4afe3"
        },
        {
          "algorithm": "SHA256",
          "checksumValue": "7b005f5476253d91f72e4c30b26e655fe26783216ef95b0531c20df182128d0b"
        }
      ]
    },
    {
      "SPDXID": "SPDXRef-File-tmp.PYkjneyP8Y-config-examples-kube-state-metrics-service.yaml",
      "fileName": "config/examples/kube-state-metrics/service.yaml",
      "copyrightText": "NOASSERTION",
      "licenseConcluded": "Apache-2.0",
      "fileTypes": [
        "TEXT"
      ],
      "licenseInfoInFiles": [
        "NONE"
      ],
      "checksums": [
        {
          "algorithm": "SHA256",
          "checksumValue": "79055fe804c19feb498957fa9ac781d095057a196fc23afdaeabd5388c93df21"
        },
        {
          "algorithm": "SHA512",
          "checksumValue": "f79a754bc5fd132a62328852ec460c9a6e52cda7dbfe296d7c344211172e48044c1546f9a72d472120bdd62774553e4ce8554b00754681b03d92b4394fa0510d"
        },
        {
          "algorithm": "SHA1",
          "checksumValue": "65173a8fdef2b42b9dd98275300b4153876da1ae"
        }
      ]
    },
    {
      "SPDXID": "SPDXRef-File-tmp.PYkjneyP8Y-tests-manifests-testudproute1.yaml",
      "fileName": "tests/manifests/testudproute1.yaml",
      "copyrightText": "NOASSERTION",
      "licenseConcluded": "Apache-2.0",
      "fileTypes": [
        "TEXT"
      ],
      "licenseInfoInFiles": [
        "NONE"
      ],
      "checksums": [
        {
          "algorithm": "SHA1",
          "checksumValue": "97dbe1c59267991bf6f4cc7f6a4145c3fe88f036"
        },
        {
          "algorithm": "SHA256",
          "checksumValue": "7b59ac5c6de177a0c84a73380ee7a0ad32739db9c7e3bfb7b8c0e0e3ae81e3b4"
        },
        {
          "algorithm": "SHA512",
          "checksumValue": "f470dcacb57ab3c186b00e9a6f52837541cec47315dc9b2ea2efe1e35022e561fe3ec2b5f9961ba459a88ca955f5cbba2508dbd0643cbf7cc1920f4340aaaaa5"
        }
      ]
    },
    {
      "SPDXID": "SPDXRef-File-tmp.PYkjneyP8Y-config-examples-kube-state-metrics-service-account.yaml",
      "fileName": "config/examples/kube-state-metrics/service-account.yaml",
      "copyrightText": "NOASSERTION",
      "licenseConcluded": "Apache-2.0",
      "fileTypes": [
        "TEXT"
      ],
      "licenseInfoInFiles": [
        "NONE"
      ],
      "checksums": [
        {
          "algorithm": "SHA1",
          "checksumValue": "54a702303272f13f6d0fdff495440d82db33e2b1"
        },
        {
          "algorithm": "SHA256",
          "checksumValue": "bb734dcf999dc9ecd0e905666c431a78bc3be0ff1cc63ed14b591a3154caa35b"
        },
        {
          "algorithm": "SHA512",
          "checksumValue": "7d9b1e960d4ea78be878df359926b41e434180ef9859589f9f3ece682009c36907df5553b58577ae707cc5a9ac7d01fac73f7c415d7ed9c9f34180fd169d7b7a"
        }
      ]
    },
    {
      "SPDXID": "SPDXRef-File-tmp.PYkjneyP8Y-config-examples-kube-prometheus-ksmC95clusterroleC95patch.yaml",
      "fileName": "config/examples/kube-prometheus/ksm_clusterrole_patch.yaml",
      "copyrightText": "NOASSERTION",
      "licenseConcluded": "Apache-2.0",
      "fileTypes": [
        "TEXT"
      ],
      "licenseInfoInFiles": [
        "NONE"
      ],
      "checksums": [
        {
          "algorithm": "SHA1",
          "checksumValue": "2422a80490cafa90b7c9a62bae4dd012449a3556"
        },
        {
          "algorithm": "SHA256",
          "checksumValue": "3217f527904f86742d506c84e7134aedbbac1e1d9ea0ffdc065c4f637a549580"
        },
        {
          "algorithm": "SHA512",
          "checksumValue": "d31397f16e169cdf876a229a71e089e98d24cd5852aafb52d036e587bbfea3ee3856feec4e73f6685c4cbb835daa560c679111ce9ad533deb9ffe8abf2bd7a56"
        }
      ]
    },
    {
      "SPDXID": "SPDXRef-File-tmp.PYkjneyP8Y-RELEASE.md",
      "fileName": "RELEASE.md",
      "copyrightText": "NOASSERTION",
      "licenseConcluded": "Apache-2.0",
      "fileTypes": [
        "TEXT",
        "DOCUMENTATION"
      ],
      "licenseInfoInFiles": [
        "NONE"
      ],
      "checksums": [
        {
          "algorithm": "SHA1",
          "checksumValue": "7f487a92f8bad6b84cf62688c5db67b4fec34f18"
        },
        {
          "algorithm": "SHA256",
          "checksumValue": "b7b9f2f52ad8137d4135fcc4695a57090ae2525dc73097ee2138c378245ca5e1"
        },
        {
          "algorithm": "SHA512",
          "checksumValue": "c3af1d6ae71d98d058b2c59c075c464c6787a4e946cf60e837837050c5f9b067b74e75b9e2b55abc2c955761b36dc416ce0cf42a0f9f384c97ec9c392a94f7ae"
        }
      ]
    },
    {
      "SPDXID": "SPDXRef-File-tmp.PYkjneyP8Y-config-examples-kube-prometheus-bundle.yaml",
      "fileName": "config/examples/kube-prometheus/bundle.yaml",
      "copyrightText": "NOASSERTION",
      "licenseConcluded": "Apache-2.0",
      "fileTypes": [
        "TEXT"
      ],
      "licenseInfoInFiles": [
        "NONE"
      ],
      "checksums": [
        {
          "algorithm": "SHA1",
          "checksumValue": "1d9526e10df0307116c1b646093be13a6fce0c51"
        },
        {
          "algorithm": "SHA256",
          "checksumValue": "aea51de28dd6a70385928017a66a20bb95a023936f11b800adcf44d11ba3ffc3"
        },
        {
          "algorithm": "SHA512",
          "checksumValue": "07931b5bb08b0c9da7fafc9f4a2f4e8114ffc24f7dd80d776381b5a32acd4fab700380ac714ec194b20b081119cc3c2831fabc1614f9e01c7dccc9bf71efac55"
        }
      ]
    },
    {
      "SPDXID": "SPDXRef-File-tmp.PYkjneyP8Y-config-gateway-api-crd-standard-gateway.networking.k8s.ioC95httproutes.yaml",
      "fileName": "config/gateway-api/crd/standard/gateway.networking.k8s.io_httproutes.yaml",
      "copyrightText": "NOASSERTION",
      "licenseConcluded": "Apache-2.0",
      "fileTypes": [
        "TEXT"
      ],
      "licenseInfoInFiles": [
        "NONE"
      ],
      "checksums": [
        {
          "algorithm": "SHA1",
          "checksumValue": "ea8110e055639f8de819d8d2867393be51035320"
        },
        {
          "algorithm": "SHA256",
          "checksumValue": "23977d470b7a5c6094ca30d929c506dc97cfbaf622d52aa3cfd6ad92934919ea"
        },
        {
          "algorithm": "SHA512",
          "checksumValue": "f732ed053298cb1544a464fd9383bf63bbe53c2c036c16d3de4addf2a22a5a9136395082b67e01a55a6215bf003fbedb0fc98db4414db4933757ea2df26d6f37"
        }
      ]
    },
    {
      "SPDXID": "SPDXRef-File-tmp.PYkjneyP8Y-config-examples-dashboards-httproutes.json",
      "fileName": "config/examples/dashboards/httproutes.json",
      "copyrightText": "NOASSERTION",
      "licenseConcluded": "Apache-2.0",
      "fileTypes": [
        "TEXT"
      ],
      "licenseInfoInFiles": [
        "NONE"
      ],
      "checksums": [
        {
          "algorithm": "SHA1",
          "checksumValue": "962d50354899fb3b3148770e72d83b473b3c6e92"
        },
        {
          "algorithm": "SHA256",
          "checksumValue": "ac90633aebf668ac64ec0367e29da03dca3dc2a018216c1ef6fe39a39d16b60e"
        },
        {
          "algorithm": "SHA512",
          "checksumValue": "838b50f7be44d03275138899a48a6ae5be70d75643473ca5d205caae26a5bb77d1a5efeac5b096a1dc8958b82f81f6c4e277e0eae5235ff9d1633fb7b5116d84"
        }
      ]
    },
    {
      "SPDXID": "SPDXRef-File-tmp.PYkjneyP8Y-config-examples-enterprise-all.yaml",
      "fileName": "config/examples/enterprise/all.yaml",
      "copyrightText": "NOASSERTION",
      "licenseConcluded": "Apache-2.0",
      "fileTypes": [
        "TEXT"
      ],
      "licenseInfoInFiles": [
        "NONE"
      ],
      "checksums": [
        {
          "algorithm": "SHA1",
          "checksumValue": "f09abdd32cb240dd9f7b3fffabe78acaefc514ec"
        },
        {
          "algorithm": "SHA256",
          "checksumValue": "4611f90bd61568e5902fc5f796664ac2352cc4ec7069458df6b21dd86e120286"
        },
        {
          "algorithm": "SHA512",
          "checksumValue": "e5cf0d120a3ab60bdd73d64e71edf9a84ef43eac3bf04fa9f00694920be028161c2403295942d594a8f63f737934e433fe04dff6dbf79ef0fed7a13426fdd5ff"
        }
      ]
    },
    {
      "SPDXID": "SPDXRef-File-tmp.PYkjneyP8Y-tests-manifests-testhttproute1.yaml",
      "fileName": "tests/manifests/testhttproute1.yaml",
      "copyrightText": "NOASSERTION",
      "licenseConcluded": "Apache-2.0",
      "fileTypes": [
        "TEXT"
      ],
      "licenseInfoInFiles": [
        "NONE"
      ],
      "checksums": [
        {
          "algorithm": "SHA512",
          "checksumValue": "60204cd1559d92c0779bb2635c04cb843f20f46fabc37ad396be034b1856d14f5ed2921540a23cd1aac9aabc70b5dcf00c1b987545cb4c3d9d350c77b09cac50"
        },
        {
          "algorithm": "SHA1",
          "checksumValue": "a3b9f1a8130563fa004c3755475c090896873b09"
        },
        {
          "algorithm": "SHA256",
          "checksumValue": "37dbc9bafb53106dfa7adf8f34d552aac746e26eddd6a6c3374a58c97b5b6a48"
        }
      ]
    },
    {
      "SPDXID": "SPDXRef-File-tmp.PYkjneyP8Y-tests-manifests-testgateway1.yaml",
      "fileName": "tests/manifests/testgateway1.yaml",
      "copyrightText": "NOASSERTION",
      "licenseConcluded": "Apache-2.0",
      "fileTypes": [
        "TEXT"
      ],
      "licenseInfoInFiles": [
        "NONE"
      ],
      "checksums": [
        {
          "algorithm": "SHA256",
          "checksumValue": "4e73f8fbaa1bc3033d51825cbb90a55244f02ff7b5430d22659e4102695b7a1d"
        },
        {
          "algorithm": "SHA512",
          "checksumValue": "01a67b83bfbd23dce80b60212cebbce530d0ecc92e566963e6075963fd84fd5372acb332788b72076ad29c1fd566d06c67f8271fa996c9e9591c11cc28ff6554"
        },
        {
          "algorithm": "SHA1",
          "checksumValue": "555431f1c704f76db0d74cc3a0ecc28a2311ad0f"
        }
      ]
    },
    {
      "SPDXID": "SPDXRef-File-tmp.PYkjneyP8Y-config-gateway-api-crd-standard-gateway.networking.k8s.ioC95tcproutes.yaml",
      "fileName": "config/gateway-api/crd/standard/gateway.networking.k8s.io_tcproutes.yaml",
      "copyrightText": "NOASSERTION",
      "licenseConcluded": "Apache-2.0",
      "fileTypes": [
        "TEXT"
      ],
      "licenseInfoInFiles": [
        "NONE"
      ],
      "checksums": [
        {
          "algorithm": "SHA512",
          "checksumValue": "7bfadc5946ab656aeb520cf758824ccc97eda994b7582944dff590c70fc7ca533bd34dc0181943fd98cfb6066833404a1a5b0224a8c319b68b9111b0109810d0"
        },
        {
          "algorithm": "SHA1",
          "checksumValue": "e86062a27e647abac1bb438ed14a26d3a615e771"
        },
        {
          "algorithm": "SHA256",
          "checksumValue": "a0ad9c8c12f62de3634409c3dda42c806c083cb77fdb35e08fae2beed2e73039"
        }
      ]
    },
    {
      "SPDXID": "SPDXRef-File-tmp.PYkjneyP8Y-kustomization.yaml",
      "fileName": "kustomization.yaml",
      "copyrightText": "NOASSERTION",
      "licenseConcluded": "Apache-2.0",
      "fileTypes": [
        "TEXT"
      ],
      "licenseInfoInFiles": [
        "NONE"
      ],
      "checksums": [
        {
          "algorithm": "SHA1",
          "checksumValue": "d03b6421fb37802ded094d3efc2dc0d8c5f417dc"
        },
        {
          "algorithm": "SHA256",
          "checksumValue": "fa4fbdb3a3c4d698deed116136be5ada4c785fad153a12a212792c9358728df8"
        },
        {
          "algorithm": "SHA512",
          "checksumValue": "3593dd0f2eabc820009935df17b2c0375d93e0841fe6e48e20898480b85a82a91327c07b43e320ff9c17992dcc1be18cbfeeae0495192420abecab9d02c2a33b"
        }
      ]
    },
    {
      "SPDXID": "SPDXRef-File-tmp.PYkjneyP8Y-tests-e2e.sh",
      "fileName": "tests/e2e.sh",
      "copyrightText": "NOASSERTION",
      "licenseConcluded": "Apache-2.0",
      "fileTypes": [
        "SOURCE"
      ],
      "licenseInfoInFiles": [
        "NONE"
      ],
      "checksums": [
        {
          "algorithm": "SHA256",
          "checksumValue": "7a6a762c16bd3a776c8f35d1c387bf241c3011f407eeba1353c0542da1f9a44d"
        },
        {
          "algorithm": "SHA512",
          "checksumValue": "08d25ef82e607078adcdba7c6176d5f9a624bf598139f2bc8bf6d6068ef6172f76342b7c5c73062039dde4ed376f4c3e5c85afa3aa9a9f77d43446979f0b143e"
        },
        {
          "algorithm": "SHA1",
          "checksumValue": "e65ae63236a7251f7687949e08f5c5b4caa716b7"
        }
      ]
    },
    {
      "SPDXID": "SPDXRef-File-tmp.PYkjneyP8Y-config-examples-kube-prometheus-ksmC95deploymentC95patch.yaml",
      "fileName": "config/examples/kube-prometheus/ksm_deployment_patch.yaml",
      "copyrightText": "NOASSERTION",
      "licenseConcluded": "Apache-2.0",
      "fileTypes": [
        "TEXT"
      ],
      "licenseInfoInFiles": [
        "NONE"
      ],
      "checksums": [
        {
          "algorithm": "SHA512",
          "checksumValue": "859111b4dbdeb291ace7cc4d3d27dae8965bb6d83733e7e9dfd67225e3f5ec2286f44dc158928b174364478693e7c114bcb92e1a2b6b6f1604886190cfda25e5"
        },
        {
          "algorithm": "SHA1",
          "checksumValue": "a742f43a3afa1655e1a38ab2cd946a320badf00c"
        },
        {
          "algorithm": "SHA256",
          "checksumValue": "180addb7468f9746ff3daa430dffd8b43641700411f0eaab7e83732e09d12bcc"
        }
      ]
    },
    {
      "SPDXID": "SPDXRef-File-tmp.PYkjneyP8Y-config-examples-dashboards-tlsroutes.json",
      "fileName": "config/examples/dashboards/tlsroutes.json",
      "copyrightText": "NOASSERTION",
      "licenseConcluded": "Apache-2.0",
      "fileTypes": [
        "TEXT"
      ],
      "licenseInfoInFiles": [
        "NONE"
      ],
      "checksums": [
        {
          "algorithm": "SHA512",
          "checksumValue": "acbba07ab46d1c840b9762942d030cc685aea0db674a66555df96753beeb5022219c0124172a4d1374962f2f571a24e3edd8800adeb2165d4c6b97f6e9458261"
        },
        {
          "algorithm": "SHA1",
          "checksumValue": "8ef7152b978b566923244afdd5dde53dbd1e0de6"
        },
        {
          "algorithm": "SHA256",
          "checksumValue": "69e64290cef96d1c8ef1f5c087be602795306d4fa035522d4e0150a54c2613b0"
        }
      ]
    },
    {
      "SPDXID": "SPDXRef-File-tmp.PYkjneyP8Y-config-gateway-api-crd-standard-gateway.networking.k8s.ioC95udproutes.yaml",
      "fileName": "config/gateway-api/crd/standard/gateway.networking.k8s.io_udproutes.yaml",
      "copyrightText": "NOASSERTION",
      "licenseConcluded": "Apache-2.0",
      "fileTypes": [
        "TEXT"
      ],
      "licenseInfoInFiles": [
        "NONE"
      ],
      "checksums": [
        {
          "algorithm": "SHA1",
          "checksumValue": "49d3684b937bee6223478875f8dbbb7b96727e93"
        },
        {
          "algorithm": "SHA256",
          "checksumValue": "b1185e28ac8fe33bf136778c0be5c5c1d122682830759f146467f1bc5827637b"
        },
        {
          "algorithm": "SHA512",
          "checksumValue": "2abc8233649118b44047b0b8679e55eb907a01615c5d50e26b63048f189c3e76fd561cd588224a46ba11a1d3d6e0733aca86cc2f0ab8874a15aef2cf152518bb"
        }
      ]
    },
    {
      "SPDXID": "SPDXRef-File-tmp.PYkjneyP8Y-config-examples-enterprise-README.md",
      "fileName": "config/examples/enterprise/README.md",
      "copyrightText": "NOASSERTION",
      "licenseConcluded": "Apache-2.0",
      "fileTypes": [
        "TEXT",
        "DOCUMENTATION"
      ],
      "licenseInfoInFiles": [
        "NONE"
      ],
      "checksums": [
        {
          "algorithm": "SHA1",
          "checksumValue": "14646cbf4070ef4993bc1ea09dfb039fc505b6bf"
        },
        {
          "algorithm": "SHA256",
          "checksumValue": "5220a9e5a9d6f563460f3cfd9e6adfd540f75bc88663f1a3ba5d3c82bc6fdd54"
        },
        {
          "algorithm": "SHA512",
          "checksumValue": "0027a564eb8d99ce11d0813715267bfc0be7297908b771380149fbcfaa6ad0aeffccf5297d7a9b53d1611b0a3a123388b4411b6e8fcb61b05e41a80dee3c1de3"
        }
      ]
    }
  ],
  "packages": [
    {
      "SPDXID": "SPDXRef-Package-tmp.PYkjneyP8Y",
      "name": "tmp.PYkjneyP8Y",
      "versionInfo": "",
      "filesAnalyzed": true,
      "licenseConcluded": "Apache-2.0",
      "downloadLocation": "NONE",
      "copyrightText": "NOASSERTION",
      "hasFiles": [
        "SPDXRef-File-tmp.PYkjneyP8Y-.gitignore",
        "SPDXRef-File-tmp.PYkjneyP8Y-.github-workflows-ci.yaml",
        "SPDXRef-File-tmp.PYkjneyP8Y-README.md",
        "SPDXRef-File-tmp.PYkjneyP8Y-RELEASE.md",
        "SPDXRef-File-tmp.PYkjneyP8Y-config-default-kustomization.yaml",
        "SPDXRef-File-tmp.PYkjneyP8Y-config-default-custom-resource-state.yaml",
        "SPDXRef-File-tmp.PYkjneyP8Y-LICENSE",
        "SPDXRef-File-tmp.PYkjneyP8Y-config-examples-dashboards-gatewayclasses.json",
        "SPDXRef-File-tmp.PYkjneyP8Y-config-examples-dashboards-grpcroutes.json",
        "SPDXRef-File-tmp.PYkjneyP8Y-Makefile",
        "SPDXRef-File-tmp.PYkjneyP8Y-config-examples-dashboards-kustomization.yaml",
        "SPDXRef-File-tmp.PYkjneyP8Y-config-examples-dashboards-httproutes.json",
        "SPDXRef-File-tmp.PYkjneyP8Y-config-examples-enterprise-README.md",
        "SPDXRef-File-tmp.PYkjneyP8Y-config-examples-dashboards-tlsroutes.json",
        "SPDXRef-File-tmp.PYkjneyP8Y-config-examples-dashboards-udproutes.json",
        "SPDXRef-File-tmp.PYkjneyP8Y-config-examples-dashboards-gateways.json",
        "SPDXRef-File-tmp.PYkjneyP8Y-config-examples-kube-prometheus-README.md",
        "SPDXRef-File-tmp.PYkjneyP8Y-config-examples-kube-prometheus-bundle-README.md",
        "SPDXRef-File-tmp.PYkjneyP8Y-config-examples-enterprise-all.yaml",
        "SPDXRef-File-tmp.PYkjneyP8Y-config-examples-dashboards-tcproutes.json",
        "SPDXRef-File-tmp.PYkjneyP8Y-config-examples-kube-prometheus-grafanaC95deploymentC95patch.yaml",
        "SPDXRef-File-tmp.PYkjneyP8Y-config-examples-kube-prometheus-ksmC95clusterroleC95patch.yaml",
        "SPDXRef-File-tmp.PYkjneyP8Y-config-examples-kube-prometheus-ksmC95deploymentC95patch.yaml",
        "SPDXRef-File-tmp.PYkjneyP8Y-config-examples-kube-prometheus-kustomization.yaml",
        "SPDXRef-File-tmp.PYkjneyP8Y-config-examples-kube-state-metrics-cluster-role-binding.yaml",
        "SPDXRef-File-tmp.PYkjneyP8Y-config-examples-kube-state-metrics-service-account.yaml",
        "SPDXRef-File-tmp.PYkjneyP8Y-config-examples-kube-state-metrics-cluster-role.yaml",
        "SPDXRef-File-tmp.PYkjneyP8Y-config-examples-kube-state-metrics-deployment.yaml",
        "SPDXRef-File-tmp.PYkjneyP8Y-config-examples-rules-kustomization.yaml",
        "SPDXRef-File-tmp.PYkjneyP8Y-config-examples-rules-alert-rules.yaml",
        "SPDXRef-File-tmp.PYkjneyP8Y-config-gateway-api-crd-standard-gateway.networking.k8s.ioC95gatewayclasses.yaml",
        "SPDXRef-File-tmp.PYkjneyP8Y-config-examples-kube-state-metrics-service.yaml",
        "SPDXRef-File-tmp.PYkjneyP8Y-config-gateway-api-crd-standard-gateway.networking.k8s.ioC95gateways.yaml",
        "SPDXRef-File-tmp.PYkjneyP8Y-config-gateway-api-crd-standard-gateway.networking.k8s.ioC95tcproutes.yaml",
        "SPDXRef-File-tmp.PYkjneyP8Y-config-gateway-api-crd-standard-gateway.networking.k8s.ioC95grpcroutes.yaml",
        "SPDXRef-File-tmp.PYkjneyP8Y-config-gateway-api-crd-standard-gateway.networking.k8s.ioC95httproutes.yaml",
        "SPDXRef-File-tmp.PYkjneyP8Y-config-gateway-api-crd-standard-gateway.networking.k8s.ioC95udproutes.yaml",
        "SPDXRef-File-tmp.PYkjneyP8Y-config-gateway-api-crd-standard-gateway.networking.k8s.ioC95tlsroutes.yaml",
        "SPDXRef-File-tmp.PYkjneyP8Y-config-gateway-api-kustomization.yaml",
        "SPDXRef-File-tmp.PYkjneyP8Y-go.mod",
        "SPDXRef-File-tmp.PYkjneyP8Y-gatewayclasses.png",
        "SPDXRef-File-tmp.PYkjneyP8Y-go.sum",
        "SPDXRef-File-tmp.PYkjneyP8Y-gateways.png",
        "SPDXRef-File-tmp.PYkjneyP8Y-grpcroutes.png",
        "SPDXRef-File-tmp.PYkjneyP8Y-kustomization.yaml",
        "SPDXRef-File-tmp.PYkjneyP8Y-config-examples-kube-prometheus-bundle.yaml",
        "SPDXRef-File-tmp.PYkjneyP8Y-httproutes.png",
        "SPDXRef-File-tmp.PYkjneyP8Y-tests-e2e.sh",
        "SPDXRef-File-tmp.PYkjneyP8Y-tests-manifests-testgateway1.yaml",
        "SPDXRef-File-tmp.PYkjneyP8Y-tcproutes.png",
        "SPDXRef-File-tmp.PYkjneyP8Y-tests-manifests-testgatewayclass1.yaml",
        "SPDXRef-File-tmp.PYkjneyP8Y-tests-manifests-testgrpcroute1.yaml",
        "SPDXRef-File-tmp.PYkjneyP8Y-tests-manifests-testhttproute1.yaml",
        "SPDXRef-File-tmp.PYkjneyP8Y-tests-manifests-testtcproute1.yaml",
        "SPDXRef-File-tmp.PYkjneyP8Y-tests-manifests-testtlsroute1.yaml",
        "SPDXRef-File-tmp.PYkjneyP8Y-tests-manifests-testudproute1.yaml",
        "SPDXRef-File-tmp.PYkjneyP8Y-tests-e2e-mainC95test.go",
        "SPDXRef-File-tmp.PYkjneyP8Y-tlsroutes.png",
        "SPDXRef-File-tmp.PYkjneyP8Y-udproutes.png",
        "SPDXRef-File-tmp.PYkjneyP8Y-config-examples-kube-prometheus-bundleC95crd.yaml"
      ],
      "licenseInfoFromFiles": [
        "Apache-2.0"
      ],
      "checksums": [],
      "packageVerificationCode": {
        "packageVerificationCodeValue": "5fe8bfbccbafc1274ae347330543fed0d227f1ed"
      }
    }
  ],
  "relationships": [
    {
      "spdxElementId": "SPDXRef-Package-tmp.PYkjneyP8Y",
      "relationshipType": "CONTAINS",
      "relatedSpdxElement": "SPDXRef-File-tmp.PYkjneyP8Y-.gitignore"
    },
    {
      "spdxElementId": "SPDXRef-Package-tmp.PYkjneyP8Y",
      "relationshipType": "CONTAINS",
      "relatedSpdxElement": "SPDXRef-File-tmp.PYkjneyP8Y-.github-workflows-ci.yaml"
    },
    {
      "spdxElementId": "SPDXRef-Package-tmp.PYkjneyP8Y",
      "relationshipType": "CONTAINS",
      "relatedSpdxElement": "SPDXRef-File-tmp.PYkjneyP8Y-README.md"
    },
    {
      "spdxElementId": "SPDXRef-Package-tmp.PYkjneyP8Y",
      "relationshipType": "CONTAINS",
      "relatedSpdxElement": "SPDXRef-File-tmp.PYkjneyP8Y-RELEASE.md"
    },
    {
      "spdxElementId": "SPDXRef-Package-tmp.PYkjneyP8Y",
      "relationshipType": "CONTAINS",
      "relatedSpdxElement": "SPDXRef-File-tmp.PYkjneyP8Y-config-default-kustomization.yaml"
    },
    {
      "spdxElementId": "SPDXRef-Package-tmp.PYkjneyP8Y",
      "relationshipType": "CONTAINS",
      "relatedSpdxElement": "SPDXRef-File-tmp.PYkjneyP8Y-config-default-custom-resource-state.yaml"
    },
    {
      "spdxElementId": "SPDXRef-Package-tmp.PYkjneyP8Y",
      "relationshipType": "CONTAINS",
      "relatedSpdxElement": "SPDXRef-File-tmp.PYkjneyP8Y-LICENSE"
    },
    {
      "spdxElementId": "SPDXRef-Package-tmp.PYkjneyP8Y",
      "relationshipType": "CONTAINS",
      "relatedSpdxElement": "SPDXRef-File-tmp.PYkjneyP8Y-config-examples-dashboards-gatewayclasses.json"
    },
    {
      "spdxElementId": "SPDXRef-Package-tmp.PYkjneyP8Y",
      "relationshipType": "CONTAINS",
      "relatedSpdxElement": "SPDXRef-File-tmp.PYkjneyP8Y-config-examples-dashboards-grpcroutes.json"
    },
    {
      "spdxElementId": "SPDXRef-Package-tmp.PYkjneyP8Y",
      "relationshipType": "CONTAINS",
      "relatedSpdxElement": "SPDXRef-File-tmp.PYkjneyP8Y-Makefile"
    },
    {
      "spdxElementId": "SPDXRef-Package-tmp.PYkjneyP8Y",
      "relationshipType": "CONTAINS",
      "relatedSpdxElement": "SPDXRef-File-tmp.PYkjneyP8Y-config-examples-dashboards-kustomization.yaml"
    },
    {
      "spdxElementId": "SPDXRef-Package-tmp.PYkjneyP8Y",
      "relationshipType": "CONTAINS",
      "relatedSpdxElement": "SPDXRef-File-tmp.PYkjneyP8Y-config-examples-dashboards-httproutes.json"
    },
    {
      "spdxElementId": "SPDXRef-Package-tmp.PYkjneyP8Y",
      "relationshipType": "CONTAINS",
      "relatedSpdxElement": "SPDXRef-File-tmp.PYkjneyP8Y-config-examples-enterprise-README.md"
    },
    {
      "spdxElementId": "SPDXRef-Package-tmp.PYkjneyP8Y",
      "relationshipType": "CONTAINS",
      "relatedSpdxElement": "SPDXRef-File-tmp.PYkjneyP8Y-config-examples-dashboards-tlsroutes.json"
    },
    {
      "spdxElementId": "SPDXRef-Package-tmp.PYkjneyP8Y",
      "relationshipType": "CONTAINS",
      "relatedSpdxElement": "SPDXRef-File-tmp.PYkjneyP8Y-config-examples-dashboards-udproutes.json"
    },
    {
      "spdxElementId": "SPDXRef-Package-tmp.PYkjneyP8Y",
      "relationshipType": "CONTAINS",
      "relatedSpdxElement": "SPDXRef-File-tmp.PYkjneyP8Y-config-examples-dashboards-gateways.json"
    },
    {
      "spdxElementId": "SPDXRef-Package-tmp.PYkjneyP8Y",
      "relationshipType": "CONTAINS",
      "relatedSpdxElement": "SPDXRef-File-tmp.PYkjneyP8Y-config-examples-kube-prometheus-README.md"
    },
    {
      "spdxElementId": "SPDXRef-Package-tmp.PYkjneyP8Y",
      "relationshipType": "CONTAINS",
      "relatedSpdxElement": "SPDXRef-File-tmp.PYkjneyP8Y-config-examples-kube-prometheus-bundle-README.md"
    },
    {
      "spdxElementId": "SPDXRef-Package-tmp.PYkjneyP8Y",
      "relationshipType": "CONTAINS",
      "relatedSpdxElement": "SPDXRef-File-tmp.PYkjneyP8Y-config-examples-enterprise-all.yaml"
    },
    {
      "spdxElementId": "SPDXRef-Package-tmp.PYkjneyP8Y",
      "relationshipType": "CONTAINS",
      "relatedSpdxElement": "SPDXRef-File-tmp.PYkjneyP8Y-config-examples-dashboards-tcproutes.json"
    },
    {
      "spdxElementId": "SPDXRef-Package-tmp.PYkjneyP8Y",
      "relationshipType": "CONTAINS",
      "relatedSpdxElement": "SPDXRef-File-tmp.PYkjneyP8Y-config-examples-kube-prometheus-grafanaC95deploymentC95patch.yaml"
    },
    {
      "spdxElementId": "SPDXRef-Package-tmp.PYkjneyP8Y",
      "relationshipType": "CONTAINS",
      "relatedSpdxElement": "SPDXRef-File-tmp.PYkjneyP8Y-config-examples-kube-prometheus-ksmC95clusterroleC95patch.yaml"
    },
    {
      "spdxElementId": "SPDXRef-Package-tmp.PYkjneyP8Y",
      "relationshipType": "CONTAINS",
      "relatedSpdxElement": "SPDXRef-File-tmp.PYkjneyP8Y-config-examples-kube-prometheus-ksmC95deploymentC95patch.yaml"
    },
    {
      "spdxElementId": "SPDXRef-Package-tmp.PYkjneyP8Y",
      "relationshipType": "CONTAINS",
      "relatedSpdxElement": "SPDXRef-File-tmp.PYkjneyP8Y-config-examples-kube-prometheus-kustomization.yaml"
    },
    {
      "spdxElementId": "SPDXRef-Package-tmp.PYkjneyP8Y",
      "relationshipType": "CONTAINS",
      "relatedSpdxElement": "SPDXRef-File-tmp.PYkjneyP8Y-config-examples-kube-state-metrics-cluster-role-binding.yaml"
    },
    {
      "spdxElementId": "SPDXRef-Package-tmp.PYkjneyP8Y",
      "relationshipType": "CONTAINS",
      "relatedSpdxElement": "SPDXRef-File-tmp.PYkjneyP8Y-config-examples-kube-state-metrics-service-account.yaml"
    },
    {
      "spdxElementId": "SPDXRef-Package-tmp.PYkjneyP8Y",
      "relationshipType": "CONTAINS",
      "relatedSpdxElement": "SPDXRef-File-tmp.PYkjneyP8Y-config-examples-kube-state-metrics-cluster-role.yaml"
    },
    {
      "spdxElementId": "SPDXRef-Package-tmp.PYkjneyP8Y",
      "relationshipType": "CONTAINS",
      "relatedSpdxElement": "SPDXRef-File-tmp.PYkjneyP8Y-config-examples-kube-state-metrics-deployment.yaml"
    },
    {
      "spdxElementId": "SPDXRef-Package-tmp.PYkjneyP8Y",
      "relationshipType": "CONTAINS",
      "relatedSpdxElement": "SPDXRef-File-tmp.PYkjneyP8Y-config-examples-rules-kustomization.yaml"
    },
    {
      "spdxElementId": "SPDXRef-Package-tmp.PYkjneyP8Y",
      "relationshipType": "CONTAINS",
      "relatedSpdxElement": "SPDXRef-File-tmp.PYkjneyP8Y-config-examples-rules-alert-rules.yaml"
    },
    {
      "spdxElementId": "SPDXRef-Package-tmp.PYkjneyP8Y",
      "relationshipType": "CONTAINS",
      "relatedSpdxElement": "SPDXRef-File-tmp.PYkjneyP8Y-config-gateway-api-crd-standard-gateway.networking.k8s.ioC95gatewayclasses.yaml"
    },
    {
      "spdxElementId": "SPDXRef-Package-tmp.PYkjneyP8Y",
      "relationshipType": "CONTAINS",
      "relatedSpdxElement": "SPDXRef-File-tmp.PYkjneyP8Y-config-examples-kube-state-metrics-service.yaml"
    },
    {
      "spdxElementId": "SPDXRef-Package-tmp.PYkjneyP8Y",
      "relationshipType": "CONTAINS",
      "relatedSpdxElement": "SPDXRef-File-tmp.PYkjneyP8Y-config-gateway-api-crd-standard-gateway.networking.k8s.ioC95gateways.yaml"
    },
    {
      "spdxElementId": "SPDXRef-Package-tmp.PYkjneyP8Y",
      "relationshipType": "CONTAINS",
      "relatedSpdxElement": "SPDXRef-File-tmp.PYkjneyP8Y-config-gateway-api-crd-standard-gateway.networking.k8s.ioC95tcproutes.yaml"
    },
    {
      "spdxElementId": "SPDXRef-Package-tmp.PYkjneyP8Y",
      "relationshipType": "CONTAINS",
      "relatedSpdxElement": "SPDXRef-File-tmp.PYkjneyP8Y-config-gateway-api-crd-standard-gateway.networking.k8s.ioC95grpcroutes.yaml"
    },
    {
      "spdxElementId": "SPDXRef-Package-tmp.PYkjneyP8Y",
      "relationshipType": "CONTAINS",
      "relatedSpdxElement": "SPDXRef-File-tmp.PYkjneyP8Y-config-gateway-api-crd-standard-gateway.networking.k8s.ioC95httproutes.yaml"
    },
    {
      "spdxElementId": "SPDXRef-Package-tmp.PYkjneyP8Y",
      "relationshipType": "CONTAINS",
      "relatedSpdxElement": "SPDXRef-File-tmp.PYkjneyP8Y-config-gateway-api-crd-standard-gateway.networking.k8s.ioC95udproutes.yaml"
    },
    {
      "spdxElementId": "SPDXRef-Package-tmp.PYkjneyP8Y",
      "relationshipType": "CONTAINS",
      "relatedSpdxElement": "SPDXRef-File-tmp.PYkjneyP8Y-config-gateway-api-crd-standard-gateway.networking.k8s.ioC95tlsroutes.yaml"
    },
    {
      "spdxElementId": "SPDXRef-Package-tmp.PYkjneyP8Y",
      "relationshipType": "CONTAINS",
      "relatedSpdxElement": "SPDXRef-File-tmp.PYkjneyP8Y-config-gateway-api-kustomization.yaml"
    },
    {
      "spdxElementId": "SPDXRef-Package-tmp.PYkjneyP8Y",
      "relationshipType": "CONTAINS",
      "relatedSpdxElement": "SPDXRef-File-tmp.PYkjneyP8Y-go.mod"
    },
    {
      "spdxElementId": "SPDXRef-Package-tmp.PYkjneyP8Y",
      "relationshipType": "CONTAINS",
      "relatedSpdxElement": "SPDXRef-File-tmp.PYkjneyP8Y-gatewayclasses.png"
    },
    {
      "spdxElementId": "SPDXRef-Package-tmp.PYkjneyP8Y",
      "relationshipType": "CONTAINS",
      "relatedSpdxElement": "SPDXRef-File-tmp.PYkjneyP8Y-go.sum"
    },
    {
      "spdxElementId": "SPDXRef-Package-tmp.PYkjneyP8Y",
      "relationshipType": "CONTAINS",
      "relatedSpdxElement": "SPDXRef-File-tmp.PYkjneyP8Y-gateways.png"
    },
    {
      "spdxElementId": "SPDXRef-Package-tmp.PYkjneyP8Y",
      "relationshipType": "CONTAINS",
      "relatedSpdxElement": "SPDXRef-File-tmp.PYkjneyP8Y-grpcroutes.png"
    },
    {
      "spdxElementId": "SPDXRef-Package-tmp.PYkjneyP8Y",
      "relationshipType": "CONTAINS",
      "relatedSpdxElement": "SPDXRef-File-tmp.PYkjneyP8Y-kustomization.yaml"
    },
    {
      "spdxElementId": "SPDXRef-Package-tmp.PYkjneyP8Y",
      "relationshipType": "CONTAINS",
      "relatedSpdxElement": "SPDXRef-File-tmp.PYkjneyP8Y-config-examples-kube-prometheus-bundle.yaml"
    },
    {
      "spdxElementId": "SPDXRef-Package-tmp.PYkjneyP8Y",
      "relationshipType": "CONTAINS",
      "relatedSpdxElement": "SPDXRef-File-tmp.PYkjneyP8Y-httproutes.png"
    },
    {
      "spdxElementId": "SPDXRef-Package-tmp.PYkjneyP8Y",
      "relationshipType": "CONTAINS",
      "relatedSpdxElement": "SPDXRef-File-tmp.PYkjneyP8Y-tests-e2e.sh"
    },
    {
      "spdxElementId": "SPDXRef-Package-tmp.PYkjneyP8Y",
      "relationshipType": "CONTAINS",
      "relatedSpdxElement": "SPDXRef-File-tmp.PYkjneyP8Y-tests-manifests-testgateway1.yaml"
    },
    {
      "spdxElementId": "SPDXRef-Package-tmp.PYkjneyP8Y",
      "relationshipType": "CONTAINS",
      "relatedSpdxElement": "SPDXRef-File-tmp.PYkjneyP8Y-tcproutes.png"
    },
    {
      "spdxElementId": "SPDXRef-Package-tmp.PYkjneyP8Y",
      "relationshipType": "CONTAINS",
      "relatedSpdxElement": "SPDXRef-File-tmp.PYkjneyP8Y-tests-manifests-testgatewayclass1.yaml"
    },
    {
      "spdxElementId": "SPDXRef-Package-tmp.PYkjneyP8Y",
      "relationshipType": "CONTAINS",
      "relatedSpdxElement": "SPDXRef-File-tmp.PYkjneyP8Y-tests-manifests-testgrpcroute1.yaml"
    },
    {
      "spdxElementId": "SPDXRef-Package-tmp.PYkjneyP8Y",
      "relationshipType": "CONTAINS",
      "relatedSpdxElement": "SPDXRef-File-tmp.PYkjneyP8Y-tests-manifests-testhttproute1.yaml"
    },
    {
      "spdxElementId": "SPDXRef-Package-tmp.PYkjneyP8Y",
      "relationshipType": "CONTAINS",
      "relatedSpdxElement": "SPDXRef-File-tmp.PYkjneyP8Y-tests-manifests-testtcproute1.yaml"
    },
    {
      "spdxElementId": "SPDXRef-Package-tmp.PYkjneyP8Y",
      "relationshipType": "CONTAINS",
      "relatedSpdxElement": "SPDXRef-File-tmp.PYkjneyP8Y-tests-manifests-testtlsroute1.yaml"
    },
    {
      "spdxElementId": "SPDXRef-Package-tmp.PYkjneyP8Y",
      "relationshipType": "CONTAINS",
      "relatedSpdxElement": "SPDXRef-File-tmp.PYkjneyP8Y-tests-manifests-testudproute1.yaml"
    },
    {
      "spdxElementId": "SPDXRef-Package-tmp.PYkjneyP8Y",
      "relationshipType": "CONTAINS",
      "relatedSpdxElement": "SPDXRef-File-tmp.PYkjneyP8Y-tests-e2e-mainC95test.go"
    },
    {
      "spdxElementId": "SPDXRef-Package-tmp.PYkjneyP8Y",
      "relationshipType": "CONTAINS",
      "relatedSpdxElement": "SPDXRef-File-tmp.PYkjneyP8Y-tlsroutes.png"
    },
    {
      "spdxElementId": "SPDXRef-Package-tmp.PYkjneyP8Y",
      "relationshipType": "CONTAINS",
      "relatedSpdxElement": "SPDXRef-File-tmp.PYkjneyP8Y-udproutes.png"
    },
    {
      "spdxElementId": "SPDXRef-Package-tmp.PYkjneyP8Y",
      "relationshipType": "CONTAINS",
      "relatedSpdxElement": "SPDXRef-File-tmp.PYkjneyP8Y-config-examples-kube-prometheus-bundleC95crd.yaml"
    }
  ],
  "annotations": [
    {
      "annotationDate": "2026-03-06T19:51:59Z",
      "annotationType": "OTHER",
      "annotator": "Tool: cncf-automation",
      "comment": "Repository: kuadrant/gateway-api-state-metrics\nVersion: 0.3.0"
    }
  ],
  "hasExtractedLicensingInfo": []
}
